odoo/addons/l10n_th_account_tax/README.rst
odoo/addons/l10n_th_account_tax/__init__.py
odoo/addons/l10n_th_account_tax/__manifest__.py
odoo/addons/l10n_th_account_tax/data/pit_rate_data.xml
odoo/addons/l10n_th_account_tax/data/withholding_tax_cert_data.xml
odoo/addons/l10n_th_account_tax/data/withholding_tax_type_income_data.xml
odoo/addons/l10n_th_account_tax/i18n/l10n_th_account_tax.pot
odoo/addons/l10n_th_account_tax/models/__init__.py
odoo/addons/l10n_th_account_tax/models/account.py
odoo/addons/l10n_th_account_tax/models/account_move.py
odoo/addons/l10n_th_account_tax/models/account_move_tax_invoice.py
odoo/addons/l10n_th_account_tax/models/account_partial_reconcile.py
odoo/addons/l10n_th_account_tax/models/account_payment.py
odoo/addons/l10n_th_account_tax/models/account_tax.py
odoo/addons/l10n_th_account_tax/models/account_withholding_move.py
odoo/addons/l10n_th_account_tax/models/account_withholding_tax.py
odoo/addons/l10n_th_account_tax/models/personal_income_tax.py
odoo/addons/l10n_th_account_tax/models/product.py
odoo/addons/l10n_th_account_tax/models/res_company.py
odoo/addons/l10n_th_account_tax/models/res_config_settings.py
odoo/addons/l10n_th_account_tax/models/res_partner.py
odoo/addons/l10n_th_account_tax/models/withholding_tax_cert.py
odoo/addons/l10n_th_account_tax/readme/CONFIGURE.md
odoo/addons/l10n_th_account_tax/readme/CONTRIBUTORS.md
odoo/addons/l10n_th_account_tax/readme/DESCRIPTION.md
odoo/addons/l10n_th_account_tax/readme/USAGE.md
odoo/addons/l10n_th_account_tax/security/account_security.xml
odoo/addons/l10n_th_account_tax/security/ir.model.access.csv
odoo/addons/l10n_th_account_tax/static/description/icon.png
odoo/addons/l10n_th_account_tax/static/description/index.html
odoo/addons/l10n_th_account_tax/tests/__init__.py
odoo/addons/l10n_th_account_tax/tests/test_tax_invoice.py
odoo/addons/l10n_th_account_tax/tests/test_withholding_tax.py
odoo/addons/l10n_th_account_tax/tests/test_withholding_tax_pit.py
odoo_addon_l10n_th_account_tax-18.0.1.5.2.dist-info/METADATA
odoo_addon_l10n_th_account_tax-18.0.1.5.2.dist-info/WHEEL
odoo_addon_l10n_th_account_tax-18.0.1.5.2.dist-info/top_level.txt
odoo_addon_l10n_th_account_tax-18.0.1.5.2.dist-info/RECORD
